vwalila/__init__.py
vwalila/config.py
vwalila/decorators.py
vwalila/es_log.py
vwalila/exc.py
vwalila/frame.py
vwalila/log_exc.py
vwalila/log_obj.py
vwalila/logger_helper.py
vwalila/mq_config.py
vwalila/mqfun.py
vwalila/redisfun.py
vwalila/self_monitor.py
vwalila/signals.py
vwalila/task_manage.py
vwalila/utils/__init__.py
vwalila/utils/mongfun.py
vwalila/utils/pf.py
vwalila/utils/res_base.py
vwalila/utils/tbl_fun.py
vwalila/utils/util_datetime.py
vwalila-3.16.3.dist-info/LICENSE
vwalila-3.16.3.dist-info/METADATA
vwalila-3.16.3.dist-info/WHEEL
vwalila-3.16.3.dist-info/top_level.txt
vwalila-3.16.3.dist-info/RECORD
